regedit.py
setup.py
regedit.py.egg-info/PKG-INFO
regedit.py.egg-info/SOURCES.txt
regedit.py.egg-info/dependency_links.txt
regedit.py.egg-info/top_level.txt