Metadata-Version: 1.1
Name: regedit.py
Version: 0.11
Summary: A better Python interface to the Windows Registry
Home-page: http://github.com/reshanie/regedit.py
Author: UNKNOWN
Author-email: UNKNOWN
License: GPLv3
Keywords: registry windows c
Platform: UNKNOWN
Classifier: Programming Language :: Python :: 3
Classifier: Programming Language :: Python :: 3.3
Classifier: Programming Language :: Python :: 3.4
Classifier: Programming Language :: Python :: 3.5
Classifier: Programming Language :: Python :: 3.6
Classifier: Programming Language :: Python :: Implementation :: CPython
